ezconn/__init__.py
ezconn-0.0.5.dist-info/LICENSE
ezconn-0.0.5.dist-info/METADATA
ezconn-0.0.5.dist-info/WHEEL
ezconn-0.0.5.dist-info/top_level.txt
ezconn-0.0.5.dist-info/RECORD
